huscy/data_protection/__init__.py
huscy/data_protection/apps.py
huscy/data_protection/models.py
huscy/data_protection/serializer.py
huscy/data_protection/urls.py
huscy/data_protection/views.py
huscy/data_protection/migrations/0001_initial.py
huscy/data_protection/migrations/__init__.py
huscy.data_protection-0.4.0a9.dist-info/METADATA
huscy.data_protection-0.4.0a9.dist-info/WHEEL
huscy.data_protection-0.4.0a9.dist-info/top_level.txt
huscy.data_protection-0.4.0a9.dist-info/RECORD
